{
  "name": "ui-svg-branch",
  "description": "SvgBranch — UI factory (1:1 with the @almadar/ui svg-branch pattern).",
  "level": "atom",
  "topic": "ui/core",
  "schema": {
    "name": "ui-svg-branch",
    "version": "1.0.0",
    "description": "SvgBranch — UI factory (1:1 with the @almadar/ui svg-branch pattern).",
    "orbitals": [
      {
        "name": "SvgBranchOrbital",
        "entity": {
          "name": "SvgBranchItem",
          "persistence": "runtime",
          "fields": [
            {
              "name": "id",
              "type": "string",
              "required": true
            }
          ]
        },
        "traits": [
          {
            "name": "SvgBranchRender",
            "entityRebindable": true,
            "entityContract": {
              "requires": [],
              "provides": []
            },
            "category": "interaction",
            "linkedEntity": "SvgBranchItem",
            "stateMachine": {
              "states": [
                {
                  "name": "idle",
                  "isInitial": true
                }
              ],
              "events": [
                {
                  "key": "INIT",
                  "name": "Initialize"
                }
              ],
              "transitions": [
                {
                  "from": "idle",
                  "to": "idle",
                  "event": "INIT",
                  "effects": [
                    [
                      "render-ui",
                      "main",
                      {
                        "width": 100,
                        "className": "",
                        "size": 1,
                        "variant": "fork",
                        "x": 5,
                        "type": "svg-branch",
                        "y": 50,
                        "branches": 2,
                        "asRoot": true,
                        "color": "var(--color-primary)",
                        "height": 100,
                        "opacity": 1
                      }
                    ]
                  ]
                }
              ]
            },
            "config": {
              "color": {
                "type": "string",
                "default": "var(--color-primary)",
                "label": "Color",
                "description": "color prop",
                "tier": "presentation"
              },
              "y": {
                "type": "number",
                "default": 50,
                "label": "Y",
                "description": "y prop",
                "tier": "presentation"
              },
              "asRoot": {
                "type": "boolean",
                "default": true,
                "label": "As Root",
                "description": "When true (default), wraps in a standalone <svg> so the shape is visible without a parent SVG context.",
                "tier": "presentation"
              },
              "width": {
                "type": "number",
                "default": 100,
                "label": "Width",
                "description": "width prop",
                "tier": "presentation"
              },
              "size": {
                "type": "number",
                "default": 1,
                "label": "Size",
                "description": "size prop",
                "tier": "presentation"
              },
              "variant": {
                "type": "string",
                "default": "fork",
                "label": "Variant",
                "description": "variant prop",
                "tier": "presentation",
                "values": [
                  "fork",
                  "merge",
                  "diamond"
                ]
              },
              "branches": {
                "type": "number",
                "default": 2,
                "label": "Branches",
                "description": "branches prop",
                "tier": "presentation"
              },
              "height": {
                "type": "number",
                "default": 100,
                "label": "Height",
                "description": "height prop",
                "tier": "presentation"
              },
              "className": {
                "type": "string",
                "default": "",
                "label": "Class Name",
                "description": "className prop",
                "tier": "presentation"
              },
              "opacity": {
                "type": "number",
                "default": 1,
                "label": "Opacity",
                "description": "opacity prop",
                "tier": "presentation"
              },
              "x": {
                "type": "number",
                "default": 5,
                "label": "X",
                "description": "x prop",
                "tier": "presentation"
              }
            },
            "scope": "instance"
          }
        ],
        "pages": [
          {
            "name": "SvgBranchPage",
            "path": "/svg-branch",
            "traits": [
              {
                "ref": "SvgBranchRender"
              }
            ]
          }
        ]
      }
    ],
    "_metadata": {
      "configProvenance": {
        "SvgBranchOrbital": [
          {
            "trait": "SvgBranchRender",
            "patternPath": "root",
            "prop": "width",
            "knob": "width"
          },
          {
            "trait": "SvgBranchRender",
            "patternPath": "root",
            "prop": "className",
            "knob": "className"
          },
          {
            "trait": "SvgBranchRender",
            "patternPath": "root",
            "prop": "size",
            "knob": "size"
          },
          {
            "trait": "SvgBranchRender",
            "patternPath": "root",
            "prop": "variant",
            "knob": "variant"
          },
          {
            "trait": "SvgBranchRender",
            "patternPath": "root",
            "prop": "x",
            "knob": "x"
          },
          {
            "trait": "SvgBranchRender",
            "patternPath": "root",
            "prop": "y",
            "knob": "y"
          },
          {
            "trait": "SvgBranchRender",
            "patternPath": "root",
            "prop": "branches",
            "knob": "branches"
          },
          {
            "trait": "SvgBranchRender",
            "patternPath": "root",
            "prop": "asRoot",
            "knob": "asRoot"
          },
          {
            "trait": "SvgBranchRender",
            "patternPath": "root",
            "prop": "color",
            "knob": "color"
          },
          {
            "trait": "SvgBranchRender",
            "patternPath": "root",
            "prop": "height",
            "knob": "height"
          },
          {
            "trait": "SvgBranchRender",
            "patternPath": "root",
            "prop": "opacity",
            "knob": "opacity"
          }
        ]
      }
    }
  },
  "source": "",
  "lolo": ""
}