{
  "name": "ui-tooltip",
  "description": "Tooltip — UI factory (1:1 with the @almadar/ui tooltip pattern).",
  "level": "molecule",
  "topic": "ui/core",
  "schema": {
    "name": "ui-tooltip",
    "version": "1.0.0",
    "description": "Tooltip — UI factory (1:1 with the @almadar/ui tooltip pattern).",
    "orbitals": [
      {
        "name": "TooltipOrbital",
        "entity": {
          "name": "TooltipItem",
          "persistence": "runtime",
          "fields": [
            {
              "name": "id",
              "type": "string",
              "required": true
            }
          ]
        },
        "traits": [
          {
            "name": "TooltipRender",
            "entityRebindable": true,
            "entityContract": {
              "requires": [],
              "provides": []
            },
            "category": "interaction",
            "linkedEntity": "TooltipItem",
            "stateMachine": {
              "states": [
                {
                  "name": "idle",
                  "isInitial": true
                }
              ],
              "events": [
                {
                  "key": "INIT",
                  "name": "Initialize"
                }
              ],
              "transitions": [
                {
                  "from": "idle",
                  "to": "idle",
                  "event": "INIT",
                  "effects": [
                    [
                      "render-ui",
                      "main",
                      {
                        "className": "",
                        "showArrow": true,
                        "hideDelay": 0,
                        "position": "top",
                        "children": [
                          {
                            "type": "typography",
                            "content": "Sample content"
                          }
                        ],
                        "content": [
                          {
                            "content": "Content",
                            "type": "typography"
                          }
                        ],
                        "delay": 200,
                        "type": "tooltip"
                      }
                    ]
                  ]
                }
              ]
            },
            "config": {
              "delay": {
                "type": "number",
                "default": 200,
                "label": "Delay",
                "description": "Show delay in milliseconds",
                "tier": "presentation"
              },
              "position": {
                "type": "string",
                "default": "top",
                "label": "Position",
                "description": "Tooltip position",
                "tier": "presentation",
                "values": [
                  "top",
                  "bottom",
                  "left",
                  "right"
                ]
              },
              "className": {
                "type": "string",
                "default": "",
                "label": "Class Name",
                "description": "Additional CSS classes",
                "tier": "presentation"
              },
              "hideDelay": {
                "type": "number",
                "default": 0,
                "label": "Hide Delay",
                "description": "Hide delay in milliseconds",
                "tier": "presentation"
              },
              "showArrow": {
                "type": "boolean",
                "default": true,
                "label": "Show Arrow",
                "description": "Show arrow",
                "tier": "presentation"
              }
            },
            "scope": "instance"
          }
        ],
        "pages": [
          {
            "name": "TooltipPage",
            "path": "/tooltip",
            "traits": [
              {
                "ref": "TooltipRender"
              }
            ]
          }
        ]
      }
    ],
    "_metadata": {
      "configProvenance": {
        "TooltipOrbital": [
          {
            "trait": "TooltipRender",
            "patternPath": "root",
            "prop": "className",
            "knob": "className"
          },
          {
            "trait": "TooltipRender",
            "patternPath": "root",
            "prop": "showArrow",
            "knob": "showArrow"
          },
          {
            "trait": "TooltipRender",
            "patternPath": "root",
            "prop": "hideDelay",
            "knob": "hideDelay"
          },
          {
            "trait": "TooltipRender",
            "patternPath": "root",
            "prop": "position",
            "knob": "position"
          },
          {
            "trait": "TooltipRender",
            "patternPath": "root",
            "prop": "delay",
            "knob": "delay"
          }
        ]
      }
    }
  },
  "source": "",
  "lolo": ""
}